randonneur/__init__.py
randonneur/config.py
randonneur/constants.py
randonneur/datapackage.py
randonneur/edge_functions.py
randonneur/edges.py
randonneur/errors.py
randonneur/generic_transformation.py
randonneur/licenses.py
randonneur/node_functions.py
randonneur/nodes.py
randonneur/templates.py
randonneur/utils.py
randonneur/validation.py
randonneur-0.7.2.dist-info/licenses/LICENSE
randonneur-0.7.2.dist-info/METADATA
randonneur-0.7.2.dist-info/WHEEL
randonneur-0.7.2.dist-info/top_level.txt
randonneur-0.7.2.dist-info/RECORD
